NekrodWidgets/__init__.py
NekrodWidgets/color_select_button.py
NekrodWidgets-0.0.3.4.dist-info/LICENSE
NekrodWidgets-0.0.3.4.dist-info/METADATA
NekrodWidgets-0.0.3.4.dist-info/WHEEL
NekrodWidgets-0.0.3.4.dist-info/top_level.txt
NekrodWidgets-0.0.3.4.dist-info/RECORD
