Metadata-Version: 2.1
Name: NekrodWidgets
Version: 0.0.3.4
Summary: Library of additional widgets for PySide6
Home-page: https://github.com/NekrodNIK/NekrodWidgets
Author: NekrodNIK
License: UNKNOWN
Platform: UNKNOWN
Classifier: Programming Language :: Python :: 3
Classifier: License :: OSI Approved :: MIT License
Classifier: Operating System :: OS Independent
Requires-Python: >=3.6
License-File: LICENSE
Requires-Dist: PySide6
Requires-Dist: importlib
